{
  "annotations": {
    "list": [
      {
        "builtIn": 1,
        "datasource": "-- Grafana --",
        "enable": true,
        "hide": true,
        "iconColor": "rgba(0, 211, 255, 1)",
        "name": "Annotations & Alerts",
        "type": "dashboard"
      }
    ]
  },
  "editable": true,
  "gnetId": null,
  "graphTooltip": 0,
  "id": 3,
  "iteration": 1597653810638,
  "links": [],
  "panels": [
    {
      "content": "\n<h1><p style=\"text-align: center;\">Google Campaign Manager</p></h1>\n\n<hr class=\"rounded\">\n",
      "datasource": null,
      "fieldConfig": {
        "defaults": {
          "custom": {}
        },
        "overrides": []
      },
      "gridPos": {
        "h": 2,
        "w": 24,
        "x": 0,
        "y": 0
      },
      "id": 2,
      "mode": "html",
      "timeFrom": null,
      "timeShift": null,
      "title": "",
      "transparent": true,
      "type": "text"
    },
    {
      "datasource": "MySQL",
      "description": "Total cost i DKK",
      "fieldConfig": {
        "defaults": {
          "custom": {},
          "mappings": [],
          "thresholds": {
            "mode": "percentage",
            "steps": [
              {
                "color": "#eab839",
                "value": null
              }
            ]
          },
          "unit": "short"
        },
        "overrides": []
      },
      "gridPos": {
        "h": 6,
        "w": 6,
        "x": 3,
        "y": 2
      },
      "id": 30,
      "options": {
        "colorMode": "value",
        "graphMode": "area",
        "justifyMode": "auto",
        "orientation": "auto",
        "reduceOptions": {
          "calcs": [
            "mean"
          ],
          "values": true
        }
      },
      "pluginVersion": "7.0.0",
      "targets": [
        {
          "format": "time_series",
          "group": [],
          "metricColumn": "none",
          "rawQuery": true,
          "rawSql": "SELECT\n  $__timeGroupAlias(date,$__interval),\n  sum(media_cost + dbm_cost) AS \"media_cost\"\nFROM google_cm_campaign_report AS gccr\nLEFT JOIN google_cm_programmatic_dim AS gcpd\nON gccr.`campaign_name` = gcpd.`campaign_name`\nWHERE\n  $__timeFilter(date) AND\n  brand in(Brand) AND \n  product in(Product) AND \n  gccr.campaign_name in($Campaign) AND \n  advertiser in($Advertiser) AND\n  buy_type in($Programmatic)",
          "refId": "A",
          "select": [
            [
              {
                "params": [
                  "HR_Probability"
                ],
                "type": "column"
              }
            ]
          ],
          "table": "ml_handset_replacement",
          "timeColumn": "Updatetime",
          "timeColumnType": "timestamp",
          "where": [
            {
              "name": "$__timeFilter",
              "params": [],
              "type": "macro"
            }
          ]
        }
      ],
      "timeFrom": null,
      "timeShift": null,
      "title": "Media Spend",
      "transparent": true,
      "type": "stat"
    },
    {
      "datasource": "MySQL",
      "description": "An action that's counted when someone interacts with your ad (for example, clicks a text ad or views a video ad) and then takes an action that you’ve defined as valuable to your business, such as an online purchase or a call to your business from a mobile phone.",
      "fieldConfig": {
        "defaults": {
          "custom": {},
          "mappings": [],
          "thresholds": {
            "mode": "percentage",
            "steps": [
              {
                "color": "#6ed0e0",
                "value": null
              }
            ]
          },
          "unit": "short"
        },
        "overrides": []
      },
      "gridPos": {
        "h": 6,
        "w": 6,
        "x": 9,
        "y": 2
      },
      "id": 28,
      "options": {
        "colorMode": "value",
        "graphMode": "area",
        "justifyMode": "auto",
        "orientation": "auto",
        "reduceOptions": {
          "calcs": [
            "mean"
          ],
          "values": true
        }
      },
      "pluginVersion": "7.0.0",
      "targets": [
        {
          "format": "time_series",
          "group": [],
          "metricColumn": "none",
          "rawQuery": true,
          "rawSql": "SELECT\n  $__timeGroupAlias(date,$__interval),\n  sum(conversions_value) AS \"conversions_value\"\nFROM google_cm_conversion_report gccr\nLEFT JOIN google_cm_programmatic_dim AS gcpd\nON gccr.`campaign_name` = gcpd.`campaign_name`\nWHERE\n  $__timeFilter(date) AND\n  brand in(Brand) AND \n  product in(Product) AND \n  gccr.campaign_name in($Campaign) AND \n  advertiser in($Advertiser) AND\n  buy_type in($Programmatic)",
          "refId": "A",
          "select": [
            [
              {
                "params": [
                  "HR_Probability"
                ],
                "type": "column"
              }
            ]
          ],
          "table": "ml_handset_replacement",
          "timeColumn": "Updatetime",
          "timeColumnType": "timestamp",
          "where": [
            {
              "name": "$__timeFilter",
              "params": [],
              "type": "macro"
            }
          ]
        }
      ],
      "timeFrom": null,
      "timeShift": null,
      "title": "Conversion Value",
      "transparent": true,
      "type": "stat"
    },
    {
      "datasource": "MySQL",
      "description": "The number of clicks",
      "fieldConfig": {
        "defaults": {
          "custom": {},
          "mappings": [],
          "thresholds": {
            "mode": "percentage",
            "steps": [
              {
                "color": "green",
                "value": null
              }
            ]
          },
          "unit": "short"
        },
        "overrides": []
      },
      "gridPos": {
        "h": 6,
        "w": 6,
        "x": 15,
        "y": 2
      },
      "id": 26,
      "options": {
        "colorMode": "value",
        "graphMode": "area",
        "justifyMode": "auto",
        "orientation": "auto",
        "reduceOptions": {
          "calcs": [
            "mean"
          ],
          "values": true
        }
      },
      "pluginVersion": "7.0.0",
      "targets": [
        {
          "format": "time_series",
          "group": [],
          "metricColumn": "none",
          "rawQuery": true,
          "rawSql": "SELECT\n  $__timeGroupAlias(date,$__interval),\n  sum(clicks) AS \"clicks\"\nFROM google_cm_campaign_report AS gccr\nLEFT JOIN google_cm_programmatic_dim AS gcpd\nON gccr.`campaign_name` = gcpd.`campaign_name`\nWHERE\n  $__timeFilter(date) AND\n  brand in(Brand) AND \n  product in(Product) AND \n  gccr.campaign_name in($Campaign) AND \n  advertiser in($Advertiser) AND\n  buy_type in($Programmatic)",
          "refId": "A",
          "select": [
            [
              {
                "params": [
                  "HR_Probability"
                ],
                "type": "column"
              }
            ]
          ],
          "table": "ml_handset_replacement",
          "timeColumn": "Updatetime",
          "timeColumnType": "timestamp",
          "where": [
            {
              "name": "$__timeFilter",
              "params": [],
              "type": "macro"
            }
          ]
        }
      ],
      "timeFrom": null,
      "timeShift": null,
      "title": "Clicks",
      "transparent": true,
      "type": "stat"
    },
    {
      "content": "\n<h1><p style=\"text-align: center;\">Google Statistics - Campaign View</p></h1>\n\n<hr class=\"rounded\">\n",
      "datasource": null,
      "description": "",
      "fieldConfig": {
        "defaults": {
          "custom": {}
        },
        "overrides": []
      },
      "gridPos": {
        "h": 2,
        "w": 12,
        "x": 6,
        "y": 8
      },
      "id": 6,
      "mode": "html",
      "timeFrom": null,
      "timeShift": null,
      "title": "",
      "transparent": true,
      "type": "text"
    },
    {
      "aliasColors": {},
      "bars": false,
      "dashLength": 10,
      "dashes": false,
      "datasource": "MySQL",
      "description": "Cost in DKK",
      "fieldConfig": {
        "defaults": {
          "custom": {},
          "mappings": [],
          "thresholds": {
            "mode": "percentage",
            "steps": [
              {
                "color": "super-light-blue",
                "value": null
              },
              {
                "color": "dark-blue",
                "value": 60
              }
            ]
          },
          "unit": "none"
        },
        "overrides": []
      },
      "fill": 1,
      "fillGradient": 0,
      "gridPos": {
        "h": 8,
        "w": 12,
        "x": 6,
        "y": 10
      },
      "hiddenSeries": false,
      "id": 4,
      "legend": {
        "avg": false,
        "current": false,
        "max": false,
        "min": false,
        "show": true,
        "total": false,
        "values": false
      },
      "lines": true,
      "linewidth": 1,
      "nullPointMode": "null as zero",
      "options": {
        "dataLinks": []
      },
      "percentage": false,
      "pluginVersion": "7.0.0",
      "pointradius": 2,
      "points": false,
      "renderer": "flot",
      "seriesOverrides": [],
      "spaceLength": 10,
      "stack": false,
      "steppedLine": false,
      "targets": [
        {
          "format": "time_series",
          "group": [],
          "metricColumn": "none",
          "rawQuery": true,
          "rawSql": "SELECT\n  $__timeGroupAlias(date,$__interval),\n  sum(media_cost + dbm_cost) AS \"media_cost\",\n  gccr.campaign_name\nFROM google_cm_campaign_report as gccr\nLEFT JOIN google_cm_programmatic_dim AS gcpd\nON gccr.`campaign_name` = gcpd.`campaign_name`\nWHERE\n  $__timeFilter(date) AND\n  brand in(Brand) AND \n  product in(Product) AND \n  gccr.campaign_name in($Campaign) AND \n  advertiser in($Advertiser) AND\n  buy_type in($Programmatic)\nGROUP BY time, gccr.campaign_name\nORDER BY time",
          "refId": "A",
          "select": [
            [
              {
                "params": [
                  "clicks"
                ],
                "type": "column"
              }
            ]
          ],
          "table": "google_campaign_report",
          "timeColumn": "clicks",
          "timeColumnType": "int",
          "where": [
            {
              "name": "$__unixEpochFilter",
              "params": [],
              "type": "macro"
            }
          ]
        }
      ],
      "thresholds": [],
      "timeFrom": null,
      "timeRegions": [],
      "timeShift": null,
      "title": "Media Spend",
      "tooltip": {
        "shared": true,
        "sort": 2,
        "value_type": "individual"
      },
      "transformations": [
        {
          "id": "calculateField",
          "options": {
            "alias": "Total",
            "mode": "reduceRow",
            "reduce": {
              "include": [],
              "reducer": "sum"
            }
          }
        }
      ],
      "transparent": true,
      "type": "graph",
      "xaxis": {
        "buckets": null,
        "mode": "time",
        "name": null,
        "show": true,
        "values": []
      },
      "yaxes": [
        {
          "format": "short",
          "label": null,
          "logBase": 1,
          "max": null,
          "min": null,
          "show": true
        },
        {
          "format": "short",
          "label": null,
          "logBase": 1,
          "max": null,
          "min": null,
          "show": true
        }
      ],
      "yaxis": {
        "align": false,
        "alignLevel": null
      }
    },
    {
      "aliasColors": {},
      "bars": false,
      "dashLength": 10,
      "dashes": false,
      "datasource": "MySQL",
      "description": "",
      "fieldConfig": {
        "defaults": {
          "custom": {},
          "mappings": [],
          "thresholds": {
            "mode": "percentage",
            "steps": [
              {
                "color": "super-light-blue",
                "value": null
              },
              {
                "color": "dark-blue",
                "value": 60
              }
            ]
          },
          "unit": "none"
        },
        "overrides": []
      },
      "fill": 1,
      "fillGradient": 0,
      "gridPos": {
        "h": 8,
        "w": 12,
        "x": 0,
        "y": 18
      },
      "hiddenSeries": false,
      "id": 32,
      "legend": {
        "avg": false,
        "current": false,
        "max": false,
        "min": false,
        "show": true,
        "total": false,
        "values": false
      },
      "lines": true,
      "linewidth": 1,
      "nullPointMode": "null as zero",
      "options": {
        "dataLinks": []
      },
      "percentage": false,
      "pluginVersion": "7.0.0",
      "pointradius": 2,
      "points": false,
      "renderer": "flot",
      "seriesOverrides": [],
      "spaceLength": 10,
      "stack": false,
      "steppedLine": false,
      "targets": [
        {
          "format": "time_series",
          "group": [],
          "metricColumn": "none",
          "rawQuery": true,
          "rawSql": "SELECT\n  date as \"time\",\n  sum(conversions) AS \"conversions\",\n  gccr.campaign_name\nFROM google_cm_conversion_report gccr\nLEFT JOIN google_cm_programmatic_dim AS gcpd\nON gccr.`campaign_name` = gcpd.`campaign_name`\nWHERE\n  $__timeFilter(date) AND\n  brand in(Brand) AND \n  product in(Product) AND \n  gccr.campaign_name in($Campaign) AND \n  advertiser in($Advertiser) AND\n  buy_type in($Programmatic)\nGROUP BY time, gccr.campaign_name\nORDER BY time",
          "refId": "A",
          "select": [
            [
              {
                "params": [
                  "clicks"
                ],
                "type": "column"
              }
            ]
          ],
          "table": "google_campaign_report",
          "timeColumn": "clicks",
          "timeColumnType": "int",
          "where": [
            {
              "name": "$__unixEpochFilter",
              "params": [],
              "type": "macro"
            }
          ]
        }
      ],
      "thresholds": [],
      "timeFrom": null,
      "timeRegions": [],
      "timeShift": null,
      "title": "Conversions - Campaign Level",
      "tooltip": {
        "shared": true,
        "sort": 2,
        "value_type": "individual"
      },
      "transformations": [
        {
          "id": "calculateField",
          "options": {
            "alias": "Total",
            "mode": "reduceRow",
            "reduce": {
              "reducer": "sum"
            }
          }
        }
      ],
      "transparent": true,
      "type": "graph",
      "xaxis": {
        "buckets": null,
        "mode": "time",
        "name": null,
        "show": true,
        "values": []
      },
      "yaxes": [
        {
          "format": "short",
          "label": null,
          "logBase": 1,
          "max": null,
          "min": null,
          "show": true
        },
        {
          "format": "short",
          "label": null,
          "logBase": 1,
          "max": null,
          "min": null,
          "show": true
        }
      ],
      "yaxis": {
        "align": false,
        "alignLevel": null
      }
    },
    {
      "aliasColors": {},
      "bars": false,
      "dashLength": 10,
      "dashes": false,
      "datasource": "MySQL",
      "description": "Conversion value is a measure of the value of all the conversions given a self defined value metric",
      "fieldConfig": {
        "defaults": {
          "custom": {},
          "mappings": [],
          "thresholds": {
            "mode": "percentage",
            "steps": [
              {
                "color": "super-light-blue",
                "value": null
              },
              {
                "color": "dark-blue",
                "value": 60
              }
            ]
          },
          "unit": "none"
        },
        "overrides": []
      },
      "fill": 1,
      "fillGradient": 0,
      "gridPos": {
        "h": 8,
        "w": 12,
        "x": 12,
        "y": 18
      },
      "hiddenSeries": false,
      "id": 8,
      "legend": {
        "avg": false,
        "current": false,
        "max": false,
        "min": false,
        "show": true,
        "total": false,
        "values": false
      },
      "lines": true,
      "linewidth": 1,
      "nullPointMode": "null as zero",
      "options": {
        "dataLinks": []
      },
      "percentage": false,
      "pluginVersion": "7.0.0",
      "pointradius": 2,
      "points": false,
      "renderer": "flot",
      "seriesOverrides": [],
      "spaceLength": 10,
      "stack": false,
      "steppedLine": false,
      "targets": [
        {
          "format": "time_series",
          "group": [],
          "metricColumn": "none",
          "rawQuery": true,
          "rawSql": "SELECT\n  date as \"time\",\n  sum(conversions_value) AS \"conversions_value\",\n  campaign_name\nFROM google_cm_conversion_report\nWHERE\n  $__timeFilter(date) AND\n  brand in($Brand) AND \n  product in($Product) AND \n  campaign_name in($Campaign) AND \n  activity in ($Activity)\nGROUP BY time, campaign_name\nORDER BY time",
          "refId": "A",
          "select": [
            [
              {
                "params": [
                  "clicks"
                ],
                "type": "column"
              }
            ]
          ],
          "table": "google_campaign_report",
          "timeColumn": "clicks",
          "timeColumnType": "int",
          "where": [
            {
              "name": "$__unixEpochFilter",
              "params": [],
              "type": "macro"
            }
          ]
        }
      ],
      "thresholds": [],
      "timeFrom": null,
      "timeRegions": [],
      "timeShift": null,
      "title": "Conversion Value - Campaign Level",
      "tooltip": {
        "shared": true,
        "sort": 2,
        "value_type": "individual"
      },
      "transformations": [
        {
          "id": "calculateField",
          "options": {
            "alias": "Total",
            "mode": "reduceRow",
            "reduce": {
              "reducer": "sum"
            }
          }
        }
      ],
      "transparent": true,
      "type": "graph",
      "xaxis": {
        "buckets": null,
        "mode": "time",
        "name": null,
        "show": true,
        "values": []
      },
      "yaxes": [
        {
          "format": "short",
          "label": null,
          "logBase": 1,
          "max": null,
          "min": null,
          "show": true
        },
        {
          "format": "short",
          "label": null,
          "logBase": 1,
          "max": null,
          "min": null,
          "show": true
        }
      ],
      "yaxis": {
        "align": false,
        "alignLevel": null
      }
    },
    {
      "aliasColors": {},
      "bars": false,
      "dashLength": 10,
      "dashes": false,
      "datasource": "MySQL",
      "description": "Cost per acquisition\n",
      "fieldConfig": {
        "defaults": {
          "custom": {},
          "mappings": [],
          "thresholds": {
            "mode": "percentage",
            "steps": [
              {
                "color": "super-light-blue",
                "value": null
              },
              {
                "color": "dark-blue",
                "value": 60
              }
            ]
          },
          "unit": "none"
        },
        "overrides": []
      },
      "fill": 1,
      "fillGradient": 0,
      "gridPos": {
        "h": 8,
        "w": 12,
        "x": 0,
        "y": 26
      },
      "hiddenSeries": false,
      "id": 10,
      "legend": {
        "avg": false,
        "current": false,
        "max": false,
        "min": false,
        "show": true,
        "total": false,
        "values": false
      },
      "lines": true,
      "linewidth": 1,
      "nullPointMode": "null as zero",
      "options": {
        "dataLinks": []
      },
      "percentage": false,
      "pluginVersion": "7.0.0",
      "pointradius": 2,
      "points": false,
      "renderer": "flot",
      "seriesOverrides": [],
      "spaceLength": 10,
      "stack": false,
      "steppedLine": false,
      "targets": [
        {
          "format": "time_series",
          "group": [],
          "metricColumn": "none",
          "rawQuery": true,
          "rawSql": "WITH conversions as (\n  SELECT\n    date, campaign_name, sum(conversions) as \"conversions\"\n  FROM google_cm_conversion_report\n  WHERE \n    brand in($Brand) AND \n    product in($Product) AND \n    campaign_name in($Campaign) AND \n    activity in ($Activity)\n  GROUP BY campaign_name, date),\ncost AS (\n  SELECT campaign_name, date, sum(media_cost) as \"media_cost\"\n  FROM google_cm_campaign_report\n  WHERE \n    $__timeFilter(date) AND\n    brand in($Brand) AND \n    product in($Product) AND \n    campaign_name in($Campaign) AND \n    advertiser in($Advertiser)\n    GROUP BY campaign_name, date)\nSELECT \n  $__timeGroupAlias(conversions.date,$__interval),\n  conversions / media_cost AS \"cpa\",\n  conversions.campaign_name\nFROM conversions LEFT JOIN cost \nON conversions.campaign_name = cost.campaign_name AND conversions.date = cost.date\nLEFT JOIN google_cm_programmatic_dim AS gcpd\nON conversions.`campaign_name` = gcpd.`campaign_name`\nWHERE\n  $__timeFilter(conversions.date) AND\n  buy_type in($Programmatic)\nGROUP BY time, campaign_name",
          "refId": "B",
          "select": [
            [
              {
                "params": [
                  "clicks"
                ],
                "type": "column"
              }
            ]
          ],
          "table": "google_device_campaign_report",
          "timeColumn": "date",
          "timeColumnType": "timestamp",
          "where": [
            {
              "name": "$__timeFilter",
              "params": [],
              "type": "macro"
            }
          ]
        }
      ],
      "thresholds": [],
      "timeFrom": null,
      "timeRegions": [],
      "timeShift": null,
      "title": "CPA",
      "tooltip": {
        "shared": true,
        "sort": 2,
        "value_type": "individual"
      },
      "transformations": [
        {
          "id": "calculateField",
          "options": {
            "alias": "Mean",
            "mode": "reduceRow",
            "reduce": {
              "reducer": "mean"
            }
          }
        }
      ],
      "transparent": true,
      "type": "graph",
      "xaxis": {
        "buckets": null,
        "mode": "time",
        "name": null,
        "show": true,
        "values": []
      },
      "yaxes": [
        {
          "format": "short",
          "label": null,
          "logBase": 1,
          "max": null,
          "min": null,
          "show": true
        },
        {
          "format": "short",
          "label": null,
          "logBase": 1,
          "max": null,
          "min": null,
          "show": true
        }
      ],
      "yaxis": {
        "align": false,
        "alignLevel": null
      }
    },
    {
      "aliasColors": {},
      "bars": false,
      "dashLength": 10,
      "dashes": false,
      "datasource": "MySQL",
      "description": "Return of Ad Spend",
      "fieldConfig": {
        "defaults": {
          "custom": {},
          "mappings": [],
          "thresholds": {
            "mode": "percentage",
            "steps": [
              {
                "color": "super-light-blue",
                "value": null
              },
              {
                "color": "dark-blue",
                "value": 60
              }
            ]
          },
          "unit": "none"
        },
        "overrides": []
      },
      "fill": 1,
      "fillGradient": 0,
      "gridPos": {
        "h": 8,
        "w": 12,
        "x": 12,
        "y": 26
      },
      "hiddenSeries": false,
      "id": 12,
      "legend": {
        "avg": false,
        "current": false,
        "max": false,
        "min": false,
        "show": true,
        "total": false,
        "values": false
      },
      "lines": true,
      "linewidth": 1,
      "nullPointMode": "null as zero",
      "options": {
        "dataLinks": []
      },
      "percentage": false,
      "pluginVersion": "7.0.0",
      "pointradius": 2,
      "points": false,
      "renderer": "flot",
      "seriesOverrides": [],
      "spaceLength": 10,
      "stack": false,
      "steppedLine": false,
      "targets": [
        {
          "format": "time_series",
          "group": [],
          "metricColumn": "none",
          "rawQuery": true,
          "rawSql": "WITH conversions as (\n  SELECT\n    date, campaign_name, sum(conversions_value) as \"conversions_value\"\n  FROM google_cm_conversion_report\n  WHERE \n    brand in($Brand) AND \n    product in($Product) AND \n    campaign_name in($Campaign) AND \n    activity in ($Activity)\n  GROUP BY campaign_name, date),\ncost AS (\n  SELECT campaign_name, date, sum(media_cost) as \"media_cost\"\n  FROM google_cm_campaign_report\n  WHERE \n    $__timeFilter(date) AND\n    brand in($Brand) AND \n    product in($Product) AND \n    campaign_name in($Campaign) \n    GROUP BY campaign_name, date)\nSELECT \n  $__timeGroupAlias(conversions.date,$__interval),\n  conversions_value / media_cost AS \"roas\",\n  conversions.campaign_name\nFROM conversions LEFT JOIN cost \nON conversions.campaign_name = cost.campaign_name AND conversions.date = cost.date\nLEFT JOIN google_cm_programmatic_dim AS gcpd\nON conversions.`campaign_name` = gcpd.`campaign_name`\nWHERE\n  $__timeFilter(conversions.date) AND\n  buy_type in($Programmatic)\nGROUP BY time, campaign_name",
          "refId": "A",
          "select": [
            [
              {
                "params": [
                  "clicks"
                ],
                "type": "column"
              }
            ]
          ],
          "table": "google_campaign_report",
          "timeColumn": "clicks",
          "timeColumnType": "int",
          "where": [
            {
              "name": "$__unixEpochFilter",
              "params": [],
              "type": "macro"
            }
          ]
        }
      ],
      "thresholds": [],
      "timeFrom": null,
      "timeRegions": [],
      "timeShift": null,
      "title": "ROAS",
      "tooltip": {
        "shared": true,
        "sort": 2,
        "value_type": "individual"
      },
      "transformations": [
        {
          "id": "calculateField",
          "options": {
            "alias": "Mean",
            "mode": "reduceRow",
            "reduce": {
              "reducer": "mean"
            }
          }
        }
      ],
      "transparent": true,
      "type": "graph",
      "xaxis": {
        "buckets": null,
        "mode": "time",
        "name": null,
        "show": true,
        "values": []
      },
      "yaxes": [
        {
          "format": "short",
          "label": null,
          "logBase": 1,
          "max": null,
          "min": null,
          "show": true
        },
        {
          "format": "short",
          "label": null,
          "logBase": 1,
          "max": null,
          "min": null,
          "show": true
        }
      ],
      "yaxis": {
        "align": false,
        "alignLevel": null
      }
    },
    {
      "aliasColors": {},
      "bars": false,
      "dashLength": 10,
      "dashes": false,
      "datasource": "MySQL",
      "description": "The number of clicks",
      "fieldConfig": {
        "defaults": {
          "custom": {},
          "mappings": [],
          "thresholds": {
            "mode": "percentage",
            "steps": [
              {
                "color": "super-light-blue",
                "value": null
              },
              {
                "color": "dark-blue",
                "value": 60
              }
            ]
          },
          "unit": "none"
        },
        "overrides": []
      },
      "fill": 1,
      "fillGradient": 0,
      "gridPos": {
        "h": 8,
        "w": 12,
        "x": 0,
        "y": 34
      },
      "hiddenSeries": false,
      "id": 14,
      "legend": {
        "avg": false,
        "current": false,
        "max": false,
        "min": false,
        "show": true,
        "total": false,
        "values": false
      },
      "lines": true,
      "linewidth": 1,
      "nullPointMode": "null as zero",
      "options": {
        "dataLinks": []
      },
      "percentage": false,
      "pluginVersion": "7.0.0",
      "pointradius": 2,
      "points": false,
      "renderer": "flot",
      "seriesOverrides": [],
      "spaceLength": 10,
      "stack": false,
      "steppedLine": false,
      "targets": [
        {
          "format": "time_series",
          "group": [],
          "metricColumn": "none",
          "rawQuery": true,
          "rawSql": "SELECT\n  $__timeGroupAlias(date,$__interval),\n  sum(clicks) AS \"clicks\",\n  gccr.campaign_name\nFROM google_cm_campaign_report gccr\nLEFT JOIN google_cm_programmatic_dim AS gcpd\nON gccr.`campaign_name` = gcpd.`campaign_name`\nWHERE\n  $__timeFilter(date) AND\n  brand in(Brand) AND \n  product in(Product) AND \n  gccr.campaign_name in($Campaign) AND \n  advertiser in($Advertiser) AND\n  buy_type in($Programmatic)\nGROUP BY time, gccr.campaign_name\nORDER BY time",
          "refId": "A",
          "select": [
            [
              {
                "params": [
                  "clicks"
                ],
                "type": "column"
              }
            ]
          ],
          "table": "google_campaign_report",
          "timeColumn": "clicks",
          "timeColumnType": "int",
          "where": [
            {
              "name": "$__unixEpochFilter",
              "params": [],
              "type": "macro"
            }
          ]
        }
      ],
      "thresholds": [],
      "timeFrom": null,
      "timeRegions": [],
      "timeShift": null,
      "title": "Clicks",
      "tooltip": {
        "shared": true,
        "sort": 2,
        "value_type": "individual"
      },
      "transformations": [
        {
          "id": "calculateField",
          "options": {
            "alias": "Total",
            "mode": "reduceRow",
            "reduce": {
              "reducer": "sum"
            }
          }
        }
      ],
      "transparent": true,
      "type": "graph",
      "xaxis": {
        "buckets": null,
        "mode": "time",
        "name": null,
        "show": true,
        "values": []
      },
      "yaxes": [
        {
          "format": "short",
          "label": null,
          "logBase": 1,
          "max": null,
          "min": null,
          "show": true
        },
        {
          "format": "short",
          "label": null,
          "logBase": 1,
          "max": null,
          "min": null,
          "show": true
        }
      ],
      "yaxis": {
        "align": false,
        "alignLevel": null
      }
    },
    {
      "aliasColors": {},
      "bars": false,
      "dashLength": 10,
      "dashes": false,
      "datasource": "MySQL",
      "description": "How often your ad is shown. An impression is counted each time your ad is shown on a search result page or other site on the Google Network.\n",
      "fieldConfig": {
        "defaults": {
          "custom": {},
          "mappings": [],
          "thresholds": {
            "mode": "percentage",
            "steps": [
              {
                "color": "super-light-blue",
                "value": null
              },
              {
                "color": "dark-blue",
                "value": 60
              }
            ]
          },
          "unit": "none"
        },
        "overrides": []
      },
      "fill": 1,
      "fillGradient": 0,
      "gridPos": {
        "h": 8,
        "w": 12,
        "x": 12,
        "y": 34
      },
      "hiddenSeries": false,
      "id": 16,
      "legend": {
        "avg": false,
        "current": false,
        "max": false,
        "min": false,
        "show": true,
        "total": false,
        "values": false
      },
      "lines": true,
      "linewidth": 1,
      "nullPointMode": "null as zero",
      "options": {
        "dataLinks": []
      },
      "percentage": false,
      "pluginVersion": "7.0.0",
      "pointradius": 2,
      "points": false,
      "renderer": "flot",
      "seriesOverrides": [],
      "spaceLength": 10,
      "stack": false,
      "steppedLine": false,
      "targets": [
        {
          "format": "time_series",
          "group": [],
          "metricColumn": "none",
          "rawQuery": true,
          "rawSql": "SELECT\n  $__timeGroupAlias(date,$__interval),\n  sum(impressions) AS \"impressions\",\n  gccr.campaign_name\nFROM google_cm_campaign_report gccr\nLEFT JOIN google_cm_programmatic_dim AS gcpd\nON gccr.`campaign_name` = gcpd.`campaign_name`\nWHERE\n  $__timeFilter(date) AND\n  brand in(Brand) AND \n  product in(Product) AND \n  gccr.campaign_name in($Campaign) AND \n  advertiser in($Advertiser) AND\n  buy_type in($Programmatic)\nGROUP BY time, gccr.campaign_name\nORDER BY time",
          "refId": "A",
          "select": [
            [
              {
                "params": [
                  "clicks"
                ],
                "type": "column"
              }
            ]
          ],
          "table": "google_campaign_report",
          "timeColumn": "clicks",
          "timeColumnType": "int",
          "where": [
            {
              "name": "$__unixEpochFilter",
              "params": [],
              "type": "macro"
            }
          ]
        }
      ],
      "thresholds": [],
      "timeFrom": null,
      "timeRegions": [],
      "timeShift": null,
      "title": "Impressions",
      "tooltip": {
        "shared": true,
        "sort": 2,
        "value_type": "individual"
      },
      "transformations": [
        {
          "id": "calculateField",
          "options": {
            "alias": "Total",
            "mode": "reduceRow",
            "reduce": {
              "reducer": "sum"
            }
          }
        }
      ],
      "transparent": true,
      "type": "graph",
      "xaxis": {
        "buckets": null,
        "mode": "time",
        "name": null,
        "show": true,
        "values": []
      },
      "yaxes": [
        {
          "format": "short",
          "label": null,
          "logBase": 1,
          "max": null,
          "min": null,
          "show": true
        },
        {
          "format": "short",
          "label": null,
          "logBase": 1,
          "max": null,
          "min": null,
          "show": true
        }
      ],
      "yaxis": {
        "align": false,
        "alignLevel": null
      }
    },
    {
      "content": "\n<h1><p style=\"text-align: center;\">Google Statistics - Conversion Value View</p></h1>\n\n<hr class=\"rounded\">\n",
      "datasource": null,
      "fieldConfig": {
        "defaults": {
          "custom": {}
        },
        "overrides": []
      },
      "gridPos": {
        "h": 2,
        "w": 12,
        "x": 6,
        "y": 42
      },
      "id": 20,
      "mode": "html",
      "timeFrom": null,
      "timeShift": null,
      "title": "",
      "transparent": true,
      "type": "text"
    },
    {
      "aliasColors": {},
      "bars": false,
      "dashLength": 10,
      "dashes": false,
      "datasource": "MySQL",
      "description": "An action that's counted when someone interacts with your ad (for example, clicks a text ad or views a video ad) and then takes an action that you’ve defined as valuable to your business, such as an online purchase or a call to your business from a mobile phone.",
      "fieldConfig": {
        "defaults": {
          "custom": {}
        },
        "overrides": []
      },
      "fill": 1,
      "fillGradient": 2,
      "gridPos": {
        "h": 9,
        "w": 12,
        "x": 0,
        "y": 44
      },
      "hiddenSeries": false,
      "id": 22,
      "legend": {
        "avg": false,
        "current": false,
        "max": false,
        "min": false,
        "show": true,
        "total": false,
        "values": false
      },
      "lines": true,
      "linewidth": 1,
      "nullPointMode": "null as zero",
      "options": {
        "dataLinks": []
      },
      "percentage": false,
      "pointradius": 2,
      "points": false,
      "renderer": "flot",
      "seriesOverrides": [],
      "spaceLength": 10,
      "stack": false,
      "steppedLine": false,
      "targets": [
        {
          "format": "time_series",
          "group": [],
          "metricColumn": "none",
          "rawQuery": true,
          "rawSql": "SELECT\n  $__timeGroupAlias(date,$__interval),\n  conversions as \"conversions\",\n  activity\nFROM google_cm_conversion_report gccr\nLEFT JOIN google_cm_programmatic_dim AS gcpd\nON gccr.`campaign_name` = gcpd.`campaign_name`\nWHERE\n  $__timeFilter(date) AND\n  brand in(Brand) AND \n  product in(Product) AND \n  gccr.campaign_name in($Campaign) AND \n  advertiser in($Advertiser) AND\n  buy_type in($Programmatic)\nGROUP BY time, activity\nORDER BY time",
          "refId": "A",
          "select": [
            [
              {
                "params": [
                  "conversions"
                ],
                "type": "column"
              }
            ]
          ],
          "table": "google_campaign_report",
          "timeColumn": "date",
          "timeColumnType": "datetime",
          "where": [
            {
              "name": "$__timeFilter",
              "params": [],
              "type": "macro"
            }
          ]
        }
      ],
      "thresholds": [],
      "timeFrom": null,
      "timeRegions": [],
      "timeShift": null,
      "title": "Conversion Goals",
      "tooltip": {
        "shared": true,
        "sort": 2,
        "value_type": "individual"
      },
      "transformations": [
        {
          "id": "calculateField",
          "options": {
            "alias": "Total",
            "mode": "reduceRow",
            "reduce": {
              "reducer": "sum"
            }
          }
        }
      ],
      "transparent": true,
      "type": "graph",
      "xaxis": {
        "buckets": null,
        "mode": "time",
        "name": null,
        "show": true,
        "values": []
      },
      "yaxes": [
        {
          "format": "short",
          "label": null,
          "logBase": 1,
          "max": null,
          "min": null,
          "show": true
        },
        {
          "format": "short",
          "label": null,
          "logBase": 1,
          "max": null,
          "min": null,
          "show": true
        }
      ],
      "yaxis": {
        "align": false,
        "alignLevel": null
      }
    },
    {
      "aliasColors": {},
      "bars": false,
      "dashLength": 10,
      "dashes": false,
      "datasource": "MySQL",
      "description": "Conversion Value is a measure of the value of all the conversions given a self defined value metric",
      "fieldConfig": {
        "defaults": {
          "custom": {}
        },
        "overrides": []
      },
      "fill": 1,
      "fillGradient": 2,
      "gridPos": {
        "h": 9,
        "w": 12,
        "x": 12,
        "y": 44
      },
      "hiddenSeries": false,
      "id": 24,
      "legend": {
        "avg": false,
        "current": false,
        "max": false,
        "min": false,
        "show": true,
        "total": false,
        "values": false
      },
      "lines": true,
      "linewidth": 1,
      "nullPointMode": "null as zero",
      "options": {
        "dataLinks": []
      },
      "percentage": false,
      "pointradius": 2,
      "points": false,
      "renderer": "flot",
      "seriesOverrides": [],
      "spaceLength": 10,
      "stack": false,
      "steppedLine": false,
      "targets": [
        {
          "format": "time_series",
          "group": [],
          "metricColumn": "none",
          "rawQuery": true,
          "rawSql": "SELECT\n  $__timeGroupAlias(date,$__interval),\n  conversions_value as \"conversions_value\",\n  activity\nFROM google_cm_conversion_report gccr\nLEFT JOIN google_cm_programmatic_dim AS gcpd\nON gccr.`campaign_name` = gcpd.`campaign_name`\nWHERE\n  $__timeFilter(date) AND\n  brand in(Brand) AND \n  product in(Product) AND \n  gccr.campaign_name in($Campaign) AND \n  advertiser in($Advertiser) AND\n  buy_type in($Programmatic)\nGROUP BY time, activity\nORDER BY time DESC",
          "refId": "A",
          "select": [
            [
              {
                "params": [
                  "HR_Probability"
                ],
                "type": "column"
              }
            ]
          ],
          "table": "ml_handset_replacement",
          "timeColumn": "Updatetime",
          "timeColumnType": "timestamp",
          "where": [
            {
              "name": "$__timeFilter",
              "params": [],
              "type": "macro"
            }
          ]
        }
      ],
      "thresholds": [],
      "timeFrom": null,
      "timeRegions": [],
      "timeShift": null,
      "title": "Conversion Value",
      "tooltip": {
        "shared": true,
        "sort": 2,
        "value_type": "individual"
      },
      "transformations": [
        {
          "id": "calculateField",
          "options": {
            "alias": "Total",
            "mode": "reduceRow",
            "reduce": {
              "reducer": "sum"
            }
          }
        }
      ],
      "transparent": true,
      "type": "graph",
      "xaxis": {
        "buckets": null,
        "mode": "time",
        "name": null,
        "show": true,
        "values": []
      },
      "yaxes": [
        {
          "format": "short",
          "label": null,
          "logBase": 1,
          "max": null,
          "min": null,
          "show": true
        },
        {
          "format": "short",
          "label": null,
          "logBase": 1,
          "max": null,
          "min": null,
          "show": true
        }
      ],
      "yaxis": {
        "align": false,
        "alignLevel": null
      }
    }
  ],
  "schemaVersion": 25,
  "style": "dark",
  "tags": [],
  "templating": {
    "list": [
      {
        "allValue": null,
        "current": {
          "selected": true,
          "text": "All",
          "value": [
            "$__all"
          ]
        },
        "datasource": "MySQL",
        "definition": "SELECT DISTINCT advertiser FROM output.google_cm_campaign_report",
        "hide": 0,
        "includeAll": true,
        "label": null,
        "multi": true,
        "name": "Advertiser",
        "options": [
          {
            "selected": true,
            "text": "All",
            "value": "$__all"
          },
          {
            "selected": false,
            "text": "YOUSEE_DISPLAY",
            "value": "YOUSEE_DISPLAY"
          },
          {
            "selected": false,
            "text": "YOUSEE_AFFILIATE",
            "value": "YOUSEE_AFFILIATE"
          }
        ],
        "query": "SELECT DISTINCT advertiser FROM output.google_cm_campaign_report",
        "refresh": 0,
        "regex": "",
        "skipUrlSync": false,
        "sort": 0,
        "tagValuesQuery": "",
        "tags": [],
        "tagsQuery": "",
        "type": "query",
        "useTags": false
      },
      {
        "allValue": null,
        "current": {
          "selected": true,
          "text": "All",
          "value": [
            "$__all"
          ]
        },
        "datasource": "MySQL",
        "definition": "SELECT DISTINCT buy_type FROM output.google_cm_programmatic_dim",
        "hide": 0,
        "includeAll": true,
        "label": null,
        "multi": true,
        "name": "Programmatic",
        "options": [
          {
            "selected": true,
            "text": "All",
            "value": "$__all"
          },
          {
            "selected": false,
            "text": "Programmatic",
            "value": "Programmatic"
          },
          {
            "selected": false,
            "text": "Not defined",
            "value": "Not defined"
          },
          {
            "selected": false,
            "text": "Mixed IO and Programmatic",
            "value": "Mixed IO and Programmatic"
          },
          {
            "selected": false,
            "text": "IO",
            "value": "IO"
          }
        ],
        "query": "SELECT DISTINCT buy_type FROM output.google_cm_programmatic_dim",
        "refresh": 0,
        "regex": "",
        "skipUrlSync": false,
        "sort": 0,
        "tagValuesQuery": "",
        "tags": [],
        "tagsQuery": "",
        "type": "query",
        "useTags": false
      },
      {
        "allValue": null,
        "current": {
          "selected": true,
          "text": "All",
          "value": [
            "$__all"
          ]
        },
        "datasource": "MySQL",
        "definition": "SELECT DISTINCT brand FROM output.google_cm_campaign_report WHERE advertiser in($Advertiser)",
        "hide": 0,
        "includeAll": true,
        "label": null,
        "multi": true,
        "name": "Brand",
        "options": [
          {
            "selected": true,
            "text": "All",
            "value": "$__all"
          },
          {
            "selected": false,
            "text": "TDC A/S (YouSee)",
            "value": "TDC A/S (YouSee)"
          },
          {
            "selected": false,
            "text": "Testkampagne",
            "value": "Testkampagne"
          },
          {
            "selected": false,
            "text": "Yousee",
            "value": "Yousee"
          }
        ],
        "query": "SELECT DISTINCT brand FROM output.google_cm_campaign_report WHERE advertiser in($Advertiser)",
        "refresh": 0,
        "regex": "",
        "skipUrlSync": false,
        "sort": 0,
        "tagValuesQuery": "",
        "tags": [],
        "tagsQuery": "",
        "type": "query",
        "useTags": false
      },
      {
        "allValue": null,
        "current": {
          "selected": true,
          "text": "All",
          "value": [
            "$__all"
          ]
        },
        "datasource": "MySQL",
        "definition": "SELECT DISTINCT product FROM output.google_cm_campaign_report WHERE advertiser in($Advertiser) AND brand in($Brand) ",
        "hide": 0,
        "includeAll": true,
        "label": null,
        "multi": true,
        "name": "Product",
        "options": [
          {
            "selected": true,
            "text": "All",
            "value": "$__all"
          },
          {
            "selected": false,
            "text": "BB",
            "value": "BB"
          },
          {
            "selected": false,
            "text": "Image",
            "value": "Image"
          },
          {
            "selected": false,
            "text": "Mixed",
            "value": "Mixed"
          },
          {
            "selected": false,
            "text": "MV",
            "value": "MV"
          },
          {
            "selected": false,
            "text": "TV",
            "value": "TV"
          },
          {
            "selected": false,
            "text": "Xee",
            "value": "Xee"
          },
          {
            "selected": false,
            "text": "",
            "value": ""
          },
          {
            "selected": false,
            "text": "Bredbånd",
            "value": "Bredbånd"
          },
          {
            "selected": false,
            "text": "Multiple",
            "value": "Multiple"
          }
        ],
        "query": "SELECT DISTINCT product FROM output.google_cm_campaign_report WHERE advertiser in($Advertiser) AND brand in($Brand) ",
        "refresh": 0,
        "regex": "",
        "skipUrlSync": false,
        "sort": 0,
        "tagValuesQuery": "",
        "tags": [],
        "tagsQuery": "",
        "type": "query",
        "useTags": false
      },
      {
        "allValue": null,
        "current": {
          "selected": true,
          "text": "All",
          "value": [
            "$__all"
          ]
        },
        "datasource": "MySQL",
        "definition": "SELECT DISTINCT campaign_name FROM output.google_cm_campaign_report WHERE advertiser in ($Advertiser) AND brand in($Brand)  AND product in($Product)",
        "hide": 0,
        "includeAll": true,
        "label": null,
        "multi": true,
        "name": "Campaign",
        "options": [
          {
            "selected": true,
            "text": "All",
            "value": "$__all"
          },
          {
            "selected": false,
            "text": "TDC A/S (YouSee)~BB~DK~W2W5 2020~Digital / BB / Kontinuerlig / Jan 2020",
            "value": "TDC A/S (YouSee)~BB~DK~W2W5 2020~Digital / BB / Kontinuerlig / Jan 2020"
          },
          {
            "selected": false,
            "text": "TDC A/S (YouSee)~BB~DK~W45W46 2019~Geo Kampagne Aalborg / Gigaspeed / 2019",
            "value": "TDC A/S (YouSee)~BB~DK~W45W46 2019~Geo Kampagne Aalborg / Gigaspeed / 2019"
          },
          {
            "selected": false,
            "text": "TDC A/S (YouSee)~BB~DK~W45W46 2019~Geo Kampagne Amager / Gigaspeed / 2019",
            "value": "TDC A/S (YouSee)~BB~DK~W45W46 2019~Geo Kampagne Amager / Gigaspeed / 2019"
          },
          {
            "selected": false,
            "text": "TDC A/S (YouSee)~BB~DK~W46W1 2019~Digital / BB / O-kunder / 46-52 2019",
            "value": "TDC A/S (YouSee)~BB~DK~W46W1 2019~Digital / BB / O-kunder / 46-52 2019"
          },
          {
            "selected": false,
            "text": "TDC A/S (YouSee)~BB~DK~W46W1 2019~Digital / Behovstest / Nov19 - Mar20",
            "value": "TDC A/S (YouSee)~BB~DK~W46W1 2019~Digital / Behovstest / Nov19 - Mar20"
          },
          {
            "selected": false,
            "text": "TDC A/S (YouSee)~BB~DK~W47W49 2019~Digital / BB / Gigaspeed Burst 4 / W47-49 2019",
            "value": "TDC A/S (YouSee)~BB~DK~W47W49 2019~Digital / BB / Gigaspeed Burst 4 / W47-49 2019"
          },
          {
            "selected": false,
            "text": "TDC A/S (YouSee)~BB~DK~W47W49 2019~Digital / BB / Gigaspeed Burst 4 TV2 / W47-49 2019",
            "value": "TDC A/S (YouSee)~BB~DK~W47W49 2019~Digital / BB / Gigaspeed Burst 4 TV2 / W47-49 2019"
          },
          {
            "selected": false,
            "text": "TDC A/S (YouSee)~BB~DK~W4W6 2020~Digital / BB / Gigaspeed Burst 5 / W4-6 2020",
            "value": "TDC A/S (YouSee)~BB~DK~W4W6 2020~Digital / BB / Gigaspeed Burst 5 / W4-6 2020"
          },
          {
            "selected": false,
            "text": "TDC A/S (YouSee)~Image~DK~W8W11 2020~Yousee / Image / Brand kampagne / W8-11 2020~",
            "value": "TDC A/S (YouSee)~Image~DK~W8W11 2020~Yousee / Image / Brand kampagne / W8-11 2020~"
          },
          {
            "selected": false,
            "text": "TDC A/S (YouSee)~Mixed~DK~W1W5 2020~Digital / Mixed / Flyt / Jan 2020",
            "value": "TDC A/S (YouSee)~Mixed~DK~W1W5 2020~Digital / Mixed / Flyt / Jan 2020"
          },
          {
            "selected": false,
            "text": "TDC A/S (YouSee)~Mixed~DK~W1W53 2020~Affiliate",
            "value": "TDC A/S (YouSee)~Mixed~DK~W1W53 2020~Affiliate"
          },
          {
            "selected": false,
            "text": "TDC A/S (YouSee)~MV~DK~W1W14 2020~Digital / MV / Kontinuerlig / Mobil samarbejde",
            "value": "TDC A/S (YouSee)~MV~DK~W1W14 2020~Digital / MV / Kontinuerlig / Mobil samarbejde"
          },
          {
            "selected": false,
            "text": "TDC A/S (YouSee)~MV~DK~W1W4 2020~Digital / MV / Samsung A50 / W1-4 2020",
            "value": "TDC A/S (YouSee)~MV~DK~W1W4 2020~Digital / MV / Samsung A50 / W1-4 2020"
          },
          {
            "selected": false,
            "text": "TDC A/S (YouSee)~MV~DK~W1W5 2020~Digital / MV / Kontinuerlig / Jan 2020",
            "value": "TDC A/S (YouSee)~MV~DK~W1W5 2020~Digital / MV / Kontinuerlig / Jan 2020"
          },
          {
            "selected": false,
            "text": "TDC A/S (YouSee)~MV~DK~W49W51 2019~Digital / MV / Huawei  P30 Lite / W49-51 2019",
            "value": "TDC A/S (YouSee)~MV~DK~W49W51 2019~Digital / MV / Huawei  P30 Lite / W49-51 2019"
          },
          {
            "selected": false,
            "text": "TDC A/S (YouSee)~MV~DK~W6W8 2020~Yousee / MV / Huawei P30 Pro / W6-8 2020",
            "value": "TDC A/S (YouSee)~MV~DK~W6W8 2020~Yousee / MV / Huawei P30 Pro / W6-8 2020"
          },
          {
            "selected": false,
            "text": "TDC A/S (YouSee)~TV~DK~W2W4 2020~Digital / TV / TV 2020 Re-Run W2-4 2020",
            "value": "TDC A/S (YouSee)~TV~DK~W2W4 2020~Digital / TV / TV 2020 Re-Run W2-4 2020"
          },
          {
            "selected": false,
            "text": "TDC A/S (YouSee)~TV~DK~W51W1 2019~Digital / YouSee Sportsrettigheder / 19.12-05.01",
            "value": "TDC A/S (YouSee)~TV~DK~W51W1 2019~Digital / YouSee Sportsrettigheder / 19.12-05.01"
          },
          {
            "selected": false,
            "text": "TDC A/S (YouSee)~Xee~DK~W52W1 2019~Xee / Dagsejerskaber vol 2 / 25.12.19-01.01.20",
            "value": "TDC A/S (YouSee)~Xee~DK~W52W1 2019~Xee / Dagsejerskaber vol 2 / 25.12.19-01.01.20"
          },
          {
            "selected": false,
            "text": "Yousee_BB_ConceptCPH-Takeover_0619",
            "value": "Yousee_BB_ConceptCPH-Takeover_0619"
          },
          {
            "selected": false,
            "text": "Yousee_BB_Gigaspeed-Burst-1_0819",
            "value": "Yousee_BB_Gigaspeed-Burst-1_0819"
          },
          {
            "selected": false,
            "text": "Yousee_BB_Gigaspeed-Burst-3_1119",
            "value": "Yousee_BB_Gigaspeed-Burst-3_1119"
          },
          {
            "selected": false,
            "text": "Yousee_BB_Gigaspeed-Kontinuerlig_0819",
            "value": "Yousee_BB_Gigaspeed-Kontinuerlig_0819"
          },
          {
            "selected": false,
            "text": "YouSee~BB~DK~W11W20 2020~Digital / Gigaspeed / Uge 11-20 2020",
            "value": "YouSee~BB~DK~W11W20 2020~Digital / Gigaspeed / Uge 11-20 2020"
          },
          {
            "selected": false,
            "text": "YouSee~BB~DK~W21W23 2020~Digital / Gigaspeed / Uge 21-23",
            "value": "YouSee~BB~DK~W21W23 2020~Digital / Gigaspeed / Uge 21-23"
          },
          {
            "selected": false,
            "text": "YouSee~BB~DK~W27W40 2020~BB Kontinuerlig Low Funnel Digital / BB Kontinuerlig Low Funnel / 2020",
            "value": "YouSee~BB~DK~W27W40 2020~BB Kontinuerlig Low Funnel Digital / BB Kontinuerlig Low Funnel / 2020"
          },
          {
            "selected": false,
            "text": "YouSee~BB~DK~W27W40 2020~Gigaspeed kontinuerlig Digital / Gigaspeed kontinuerlig",
            "value": "YouSee~BB~DK~W27W40 2020~Gigaspeed kontinuerlig Digital / Gigaspeed kontinuerlig"
          },
          {
            "selected": false,
            "text": "YouSee~BB~DK~W32W35 2020~BB Regional Fiber Digital / BB Regional Fiber",
            "value": "YouSee~BB~DK~W32W35 2020~BB Regional Fiber Digital / BB Regional Fiber"
          },
          {
            "selected": false,
            "text": "Yousee_Bredbånd_118_1018",
            "value": "Yousee_Bredbånd_118_1018"
          },
          {
            "selected": false,
            "text": "Yousee_Bredbånd_Boligsider_0219",
            "value": "Yousee_Bredbånd_Boligsider_0219"
          },
          {
            "selected": false,
            "text": "Yousee_Bredbånd_Gigaspeed-Burst-2_0919",
            "value": "Yousee_Bredbånd_Gigaspeed-Burst-2_0919"
          },
          {
            "selected": false,
            "text": "Yousee_Bredbånd_Positionering_1018",
            "value": "Yousee_Bredbånd_Positionering_1018"
          },
          {
            "selected": false,
            "text": "YouSee~Image~DK~W18W22 2020~Digital / Brand / Uge 18-22",
            "value": "YouSee~Image~DK~W18W22 2020~Digital / Brand / Uge 18-22"
          },
          {
            "selected": false,
            "text": "YouSee_Multiple_Affiliate_2018",
            "value": "YouSee_Multiple_Affiliate_2018"
          },
          {
            "selected": false,
            "text": "Yousee_Multiple_Programmatic_2019",
            "value": "Yousee_Multiple_Programmatic_2019"
          },
          {
            "selected": false,
            "text": "Yousee_MV_Huawei-P-Smart-W43-45_1119",
            "value": "Yousee_MV_Huawei-P-Smart-W43-45_1119"
          },
          {
            "selected": false,
            "text": "Yousee_MV_Huawei-P30-Lite_0919",
            "value": "Yousee_MV_Huawei-P30-Lite_0919"
          },
          {
            "selected": false,
            "text": "Yousee_MV_iPhone-11-Lancering_0919",
            "value": "Yousee_MV_iPhone-11-Lancering_0919"
          },
          {
            "selected": false,
            "text": "Yousee_MV_Iphone-Kontinuerlig_0819",
            "value": "Yousee_MV_Iphone-Kontinuerlig_0819"
          },
          {
            "selected": false,
            "text": "Yousee_MV_Mobilsamarbejder_1119",
            "value": "Yousee_MV_Mobilsamarbejder_1119"
          },
          {
            "selected": false,
            "text": "Yousee_MV_Samsung-A40_0519",
            "value": "Yousee_MV_Samsung-A40_0519"
          },
          {
            "selected": false,
            "text": "Yousee_MV_Samsung-S10_0819",
            "value": "Yousee_MV_Samsung-S10_0819"
          },
          {
            "selected": false,
            "text": "Yousee_MV_SamsungS10E_A40_1019",
            "value": "Yousee_MV_SamsungS10E_A40_1019"
          },
          {
            "selected": false,
            "text": "YouSee~MV~DK~W12W14 2020~Digital / Huawei P30 Lite / Uge 12-14 2020~",
            "value": "YouSee~MV~DK~W12W14 2020~Digital / Huawei P30 Lite / Uge 12-14 2020~"
          },
          {
            "selected": false,
            "text": "YouSee~MV~DK~W15W18 2020~Digital / iPhones / Uge 15-18~",
            "value": "YouSee~MV~DK~W15W18 2020~Digital / iPhones / Uge 15-18~"
          },
          {
            "selected": false,
            "text": "YouSee~MV~DK~W18W21 2020~Digital / Terminal Fri Data / Uge 18-21",
            "value": "YouSee~MV~DK~W18W21 2020~Digital / Terminal Fri Data / Uge 18-21"
          },
          {
            "selected": false,
            "text": "YouSee~MV~DK~W22W24 2020~Digital / Samsung A51 / U22-24~",
            "value": "YouSee~MV~DK~W22W24 2020~Digital / Samsung A51 / U22-24~"
          },
          {
            "selected": false,
            "text": "YouSee~MV~DK~W25W27 2020~Digital / iPhone 11 / U25-27",
            "value": "YouSee~MV~DK~W25W27 2020~Digital / iPhone 11 / U25-27"
          },
          {
            "selected": false,
            "text": "YouSee~MV~DK~W28W31 2020~Digital / MV iPhone / W28-31 Digital / U28-31",
            "value": "YouSee~MV~DK~W28W31 2020~Digital / MV iPhone / W28-31 Digital / U28-31"
          },
          {
            "selected": false,
            "text": "YouSee~MV~DK~W9W10 2020~Digital / Samsung S10 Lite",
            "value": "YouSee~MV~DK~W9W10 2020~Digital / Samsung S10 Lite"
          },
          {
            "selected": false,
            "text": "Yousee_TV_Bland-Selv-Re-Run_0719",
            "value": "Yousee_TV_Bland-Selv-Re-Run_0719"
          },
          {
            "selected": false,
            "text": "Yousee_TV_Bland-Selv-Re-Run_0919",
            "value": "Yousee_TV_Bland-Selv-Re-Run_0919"
          },
          {
            "selected": false,
            "text": "Yousee_TV_Bland-Selv_1119",
            "value": "Yousee_TV_Bland-Selv_1119"
          },
          {
            "selected": false,
            "text": "Yousee_TV_Premier-League-Lancering_0719",
            "value": "Yousee_TV_Premier-League-Lancering_0719"
          },
          {
            "selected": false,
            "text": "Yousee_TV_Premier-League-W30-36_0719",
            "value": "Yousee_TV_Premier-League-W30-36_0719"
          },
          {
            "selected": false,
            "text": "Yousee_TV_Xee-Dagsejerskab_1119",
            "value": "Yousee_TV_Xee-Dagsejerskab_1119"
          },
          {
            "selected": false,
            "text": "YouSee~TV~DK~W13W16 2020~Digital / Bland Selv / Uge 13-16~",
            "value": "YouSee~TV~DK~W13W16 2020~Digital / Bland Selv / Uge 13-16~"
          },
          {
            "selected": false,
            "text": "YouSee~TV~DK~W15W27 2020~Digital / TV / Kontinuerlig / 2020~",
            "value": "YouSee~TV~DK~W15W27 2020~Digital / TV / Kontinuerlig / 2020~"
          },
          {
            "selected": false,
            "text": "YouSee~TV~DK~W20W27 2020~TV Behovstest Kontinuerlig~",
            "value": "YouSee~TV~DK~W20W27 2020~TV Behovstest Kontinuerlig~"
          },
          {
            "selected": false,
            "text": "YouSee~TV~DK~W30W33 2020~Bland Selv U30-33 Digital / U30-33",
            "value": "YouSee~TV~DK~W30W33 2020~Bland Selv U30-33 Digital / U30-33"
          },
          {
            "selected": false,
            "text": "YouSee~Xee~DK~W15W15 2020~Digital / Limboland / 12.04~",
            "value": "YouSee~Xee~DK~W15W15 2020~Digital / Limboland / 12.04~"
          },
          {
            "selected": false,
            "text": "YouSee~Xee~DK~W31W31 2020~Jungle Digital / 02.08.20",
            "value": "YouSee~Xee~DK~W31W31 2020~Jungle Digital / 02.08.20"
          }
        ],
        "query": "SELECT DISTINCT campaign_name FROM output.google_cm_campaign_report WHERE advertiser in ($Advertiser) AND brand in($Brand)  AND product in($Product)",
        "refresh": 0,
        "regex": "",
        "skipUrlSync": false,
        "sort": 0,
        "tagValuesQuery": "",
        "tags": [],
        "tagsQuery": "",
        "type": "query",
        "useTags": false
      },
      {
        "allValue": null,
        "current": {
          "selected": false,
          "text": "All",
          "value": "$__all"
        },
        "datasource": "MySQL",
        "definition": "SELECT DISTINCT activity FROM output.google_cm_conversion_report WHERE advertiser in ($Advertiser) AND brand in($Brand)  AND product in($Product) AND campaign_name in($Campaign)",
        "hide": 0,
        "includeAll": true,
        "label": null,
        "multi": true,
        "name": "Activity",
        "options": [
          {
            "selected": true,
            "text": "All",
            "value": "$__all"
          },
          {
            "selected": false,
            "text": "Esportligaen_rtg_allpages",
            "value": "Esportligaen_rtg_allpages"
          },
          {
            "selected": false,
            "text": "Mobil.nu_Audience",
            "value": "Mobil.nu_Audience"
          },
          {
            "selected": false,
            "text": "Mobilsiden_Audience",
            "value": "Mobilsiden_Audience"
          },
          {
            "selected": false,
            "text": "Yousee_100-500Mbit+Knap_BB",
            "value": "Yousee_100-500Mbit+Knap_BB"
          },
          {
            "selected": false,
            "text": "YouSee_30seconds_BB",
            "value": "YouSee_30seconds_BB"
          },
          {
            "selected": false,
            "text": "YouSee_30seconds_More",
            "value": "YouSee_30seconds_More"
          },
          {
            "selected": false,
            "text": "YouSee_30seconds_MV",
            "value": "YouSee_30seconds_MV"
          },
          {
            "selected": false,
            "text": "YouSee_30seconds_TV",
            "value": "YouSee_30seconds_TV"
          },
          {
            "selected": false,
            "text": "Yousee_50-100Mbit+Knap_BB",
            "value": "Yousee_50-100Mbit+Knap_BB"
          },
          {
            "selected": false,
            "text": "Yousee_500-1000Mbit+Knap_BB",
            "value": "Yousee_500-1000Mbit+Knap_BB"
          },
          {
            "selected": false,
            "text": "YouSee_60seconds_BB",
            "value": "YouSee_60seconds_BB"
          },
          {
            "selected": false,
            "text": "YouSee_60seconds_More",
            "value": "YouSee_60seconds_More"
          },
          {
            "selected": false,
            "text": "YouSee_60seconds_MV",
            "value": "YouSee_60seconds_MV"
          },
          {
            "selected": false,
            "text": "YouSee_60seconds_TV",
            "value": "YouSee_60seconds_TV"
          },
          {
            "selected": false,
            "text": "YouSee_Allpages",
            "value": "YouSee_Allpages"
          },
          {
            "selected": false,
            "text": "Yousee_Behovstest1_page hit_mid-funnel_ikke startet test",
            "value": "Yousee_Behovstest1_page hit_mid-funnel_ikke startet test"
          },
          {
            "selected": false,
            "text": "Yousee_Behovstest2_test startet - ikke afsluttet",
            "value": "Yousee_Behovstest2_test startet - ikke afsluttet"
          },
          {
            "selected": false,
            "text": "Yousee_Behovstest3_test afsluttet og anbefaling modtaget",
            "value": "Yousee_Behovstest3_test afsluttet og anbefaling modtaget"
          },
          {
            "selected": false,
            "text": "Yousee_Behovstest3_test afsluttet_BS10",
            "value": "Yousee_Behovstest3_test afsluttet_BS10"
          },
          {
            "selected": false,
            "text": "Yousee_Behovstest3_test afsluttet_BS20",
            "value": "Yousee_Behovstest3_test afsluttet_BS20"
          },
          {
            "selected": false,
            "text": "Yousee_Behovstest3_test afsluttet_BS36",
            "value": "Yousee_Behovstest3_test afsluttet_BS36"
          },
          {
            "selected": false,
            "text": "YouSee_BrandedSearch",
            "value": "YouSee_BrandedSearch"
          },
          {
            "selected": false,
            "text": "YouSee_Conversion-All",
            "value": "YouSee_Conversion-All"
          },
          {
            "selected": false,
            "text": "YouSee_Conversion-BB",
            "value": "YouSee_Conversion-BB"
          },
          {
            "selected": false,
            "text": "YouSee_Conversion-MV",
            "value": "YouSee_Conversion-MV"
          },
          {
            "selected": false,
            "text": "YouSee_Conversion-Terminal",
            "value": "YouSee_Conversion-Terminal"
          },
          {
            "selected": false,
            "text": "YouSee_Conversion-TV",
            "value": "YouSee_Conversion-TV"
          },
          {
            "selected": false,
            "text": "YouSee_Flyttemelding i MitYouSee",
            "value": "YouSee_Flyttemelding i MitYouSee"
          },
          {
            "selected": false,
            "text": "Yousee_Internet-Speed-Calculator-Interaction_BB",
            "value": "Yousee_Internet-Speed-Calculator-Interaction_BB"
          },
          {
            "selected": false,
            "text": "Yousee_Meld-flytning",
            "value": "Yousee_Meld-flytning"
          },
          {
            "selected": false,
            "text": "YouSee_RMO-All",
            "value": "YouSee_RMO-All"
          },
          {
            "selected": false,
            "text": "YouSee_RMO-BB",
            "value": "YouSee_RMO-BB"
          },
          {
            "selected": false,
            "text": "YouSee_RMO-Fiber",
            "value": "YouSee_RMO-Fiber"
          },
          {
            "selected": false,
            "text": "YouSee_RMO-MV",
            "value": "YouSee_RMO-MV"
          },
          {
            "selected": false,
            "text": "YouSee_RMO-Terminal",
            "value": "YouSee_RMO-Terminal"
          },
          {
            "selected": false,
            "text": "YouSee_RMO-TV",
            "value": "YouSee_RMO-TV"
          },
          {
            "selected": false,
            "text": "YouSee_Semb-Konverteringer",
            "value": "YouSee_Semb-Konverteringer"
          },
          {
            "selected": false,
            "text": "Yousee_Step1_BB",
            "value": "Yousee_Step1_BB"
          },
          {
            "selected": false,
            "text": "Yousee_Step1_MV",
            "value": "Yousee_Step1_MV"
          },
          {
            "selected": false,
            "text": "Yousee_Step1_Terminal",
            "value": "Yousee_Step1_Terminal"
          },
          {
            "selected": false,
            "text": "Yousee_Step1_TV",
            "value": "Yousee_Step1_TV"
          },
          {
            "selected": false,
            "text": "YouSee_Users",
            "value": "YouSee_Users"
          },
          {
            "selected": false,
            "text": "Yousee_Wifi-Booster_1.Påbegyndt test",
            "value": "Yousee_Wifi-Booster_1.Påbegyndt test"
          },
          {
            "selected": false,
            "text": "Yousee_Wifi-Booster_page hit_mid-funnel_ikke startet test",
            "value": "Yousee_Wifi-Booster_page hit_mid-funnel_ikke startet test"
          },
          {
            "selected": false,
            "text": "Boliga_Audience",
            "value": "Boliga_Audience"
          },
          {
            "selected": false,
            "text": "Yousee_Behovstest3_test afsluttet_Grundpakke",
            "value": "Yousee_Behovstest3_test afsluttet_Grundpakke"
          },
          {
            "selected": false,
            "text": "Yousee_Wifi-Booster_test afsluttet og anbefaling modtaget",
            "value": "Yousee_Wifi-Booster_test afsluttet og anbefaling modtaget"
          },
          {
            "selected": false,
            "text": "YouSee_Gennemført_Test",
            "value": "YouSee_Gennemført_Test"
          },
          {
            "selected": false,
            "text": "YouSee_Step1_All",
            "value": "YouSee_Step1_All"
          },
          {
            "selected": false,
            "text": "Berlingske_Native-Samarbejde",
            "value": "Berlingske_Native-Samarbejde"
          }
        ],
        "query": "SELECT DISTINCT activity FROM output.google_cm_conversion_report WHERE advertiser in ($Advertiser) AND brand in($Brand)  AND product in($Product) AND campaign_name in($Campaign)",
        "refresh": 0,
        "regex": "",
        "skipUrlSync": false,
        "sort": 0,
        "tagValuesQuery": "",
        "tags": [],
        "tagsQuery": "",
        "type": "query",
        "useTags": false
      }
    ]
  },
  "time": {
    "from": "now-30d",
    "to": "now"
  },
  "timepicker": {
    "refresh_intervals": [
      "10s",
      "30s",
      "1m",
      "5m",
      "15m",
      "30m",
      "1h",
      "2h",
      "1d"
    ]
  },
  "timezone": "",
  "title": "Google Campaign Manager",
  "uid": "SMxJVGIMk",
  "version": 19
}